{"id":"35lbr2v59wfvtb19fz9m8ks","title":"Regex that ignores Latin characters","desc":"Combining two regex \"^[\\x20-\\x7E]*$\" and \"\\S(.*\\S\" into one","updated":1664736529944,"created":1659456120000,"tags":["regex","stack-overflow","answer"],"custom":{},"fname":"stack-overflow.73207214","type":"note","vault":{"fsPath":".","selfContained":true,"name":"bits-and-bobbles"},"contentHash":"185308d11fa7ef21f721a66b619b5750","links":[{"type":"frontmatterTag","from":{"fname":"stack-overflow.73207214","id":"35lbr2v59wfvtb19fz9m8ks","vaultName":"bits-and-bobbles"},"value":"tags.regex","alias":"regex","xvault":false,"to":{"fname":"tags.regex"}},{"type":"frontmatterTag","from":{"fname":"stack-overflow.73207214","id":"35lbr2v59wfvtb19fz9m8ks","vaultName":"bits-and-bobbles"},"value":"tags.stack-overflow","alias":"stack-overflow","xvault":false,"to":{"fname":"tags.stack-overflow"}},{"type":"frontmatterTag","from":{"fname":"stack-overflow.73207214","id":"35lbr2v59wfvtb19fz9m8ks","vaultName":"bits-and-bobbles"},"value":"tags.answer","alias":"answer","xvault":false,"to":{"fname":"tags.answer"}}],"anchors":{},"children":[],"parent":"djibocawvr9giosnl1nlori","data":{}}
