{"id":"eic97gqoxwq6z566eryhau7","title":"Connection Refused","desc":"","updated":1669499789930,"created":1669499789930,"tags":["evidence investigation"],"custom":{},"fname":"cybersoc.detective.connectionrefused","type":"note","vault":{"fsPath":".","selfContained":true,"name":"bits-and-bobbles"},"contentHash":"8bbbf5d2a3d905a3e749db51051851ac","links":[{"type":"frontmatterTag","from":{"fname":"cybersoc.detective.connectionrefused","id":"eic97gqoxwq6z566eryhau7","vaultName":"bits-and-bobbles"},"value":"tags.evidence investigation","alias":"evidence investigation","xvault":false,"to":{"fname":"tags.evidence investigation"}}],"anchors":{},"children":[],"parent":"puy3x8chzao44herg4r68x0","data":{}}
