{"id":"xotvh2n410zlhucecj873vv","title":"Manipulate Pandas Index column on write","desc":"How to remove Pandas Index Column when Writting to CSV","updated":1664735134988,"created":1655572560000,"tags":["python","pandas","dataframe","stack-overflow","answer"],"custom":{},"fname":"stack-overflow.72669566","type":"note","vault":{"fsPath":".","selfContained":true,"name":"bits-and-bobbles"},"contentHash":"dde5cbd3cf4cec1476114f77cd62de8e","links":[{"type":"frontmatterTag","from":{"fname":"stack-overflow.72669566","id":"xotvh2n410zlhucecj873vv","vaultName":"bits-and-bobbles"},"value":"tags.python","alias":"python","xvault":false,"to":{"fname":"tags.python"}},{"type":"frontmatterTag","from":{"fname":"stack-overflow.72669566","id":"xotvh2n410zlhucecj873vv","vaultName":"bits-and-bobbles"},"value":"tags.pandas","alias":"pandas","xvault":false,"to":{"fname":"tags.pandas"}},{"type":"frontmatterTag","from":{"fname":"stack-overflow.72669566","id":"xotvh2n410zlhucecj873vv","vaultName":"bits-and-bobbles"},"value":"tags.dataframe","alias":"dataframe","xvault":false,"to":{"fname":"tags.dataframe"}},{"type":"frontmatterTag","from":{"fname":"stack-overflow.72669566","id":"xotvh2n410zlhucecj873vv","vaultName":"bits-and-bobbles"},"value":"tags.stack-overflow","alias":"stack-overflow","xvault":false,"to":{"fname":"tags.stack-overflow"}},{"type":"frontmatterTag","from":{"fname":"stack-overflow.72669566","id":"xotvh2n410zlhucecj873vv","vaultName":"bits-and-bobbles"},"value":"tags.answer","alias":"answer","xvault":false,"to":{"fname":"tags.answer"}}],"anchors":{},"children":[],"parent":"djibocawvr9giosnl1nlori","data":{}}
